nerfbaselines/__init__.py
nerfbaselines/__main__.py
nerfbaselines/_constants.py
nerfbaselines/_export_demo.py
nerfbaselines/_method_utils.py
nerfbaselines/_metrics_lpips.py
nerfbaselines/_ray_method.py
nerfbaselines/_registry.py
nerfbaselines/_types.py
nerfbaselines/_version.py
nerfbaselines/cameras.py
nerfbaselines/evaluation.py
nerfbaselines/io.py
nerfbaselines/logging.py
nerfbaselines/metrics.json
nerfbaselines/metrics.py
nerfbaselines/palettes.json
nerfbaselines/results.py
nerfbaselines/training.py
nerfbaselines/utils.py
nerfbaselines/_lpips_weights/.gitignore
nerfbaselines/_lpips_weights/__init__.py
nerfbaselines/_lpips_weights/alex-0.1.pth
nerfbaselines/_lpips_weights/vgg-0.1.pth
nerfbaselines/backends/Dockerfile
nerfbaselines/backends/__init__.py
nerfbaselines/backends/_apptainer.py
nerfbaselines/backends/_common.py
nerfbaselines/backends/_conda.py
nerfbaselines/backends/_docker.py
nerfbaselines/backends/_rpc.py
nerfbaselines/backends/_transport_protocol.py
nerfbaselines/cli/__init__.py
nerfbaselines/cli/_build_docker_image.py
nerfbaselines/cli/_common.py
nerfbaselines/cli/_download_dataset.py
nerfbaselines/cli/_evaluate.py
nerfbaselines/cli/_export_demo.py
nerfbaselines/cli/_export_mesh.py
nerfbaselines/cli/_fix_checkpoint.py
nerfbaselines/cli/_fix_output_artifact.py
nerfbaselines/cli/_generate_dataset_results.py
nerfbaselines/cli/_install_method.py
nerfbaselines/cli/_measure_fps.py
nerfbaselines/cli/_render.py
nerfbaselines/cli/_shell.py
nerfbaselines/cli/_test_method.py
nerfbaselines/cli/_train.py
nerfbaselines/cli/_viewer.py
nerfbaselines/cli/_web.py
nerfbaselines/datasets/__init__.py
nerfbaselines/datasets/_colmap_utils.py
nerfbaselines/datasets/_common.py
nerfbaselines/datasets/blender.py
nerfbaselines/datasets/blender_spec.py
nerfbaselines/datasets/bundler.py
nerfbaselines/datasets/bundler_spec.py
nerfbaselines/datasets/colmap.py
nerfbaselines/datasets/colmap_spec.py
nerfbaselines/datasets/hierarchical_3dgs.py
nerfbaselines-1.2.12.dist-info/licenses/LICENSE
nerfbaselines-1.2.12.dist-info/METADATA
nerfbaselines-1.2.12.dist-info/WHEEL
nerfbaselines-1.2.12.dist-info/entry_points.txt
nerfbaselines-1.2.12.dist-info/top_level.txt
nerfbaselines-1.2.12.dist-info/RECORD
