Metadata-Version: 2.4
Name: nerfbaselines
Version: 1.2.12
Summary: Reproducible evaluation of NeRF and 3DGS methods
Author-email: Jonas Kulhanek <jonas.kulhanek@live.com>
License: MIT
Project-URL: Documentation, https://nerfbaselines.github.io/docs
Project-URL: Source, https://github.com/nerfbaselines/nerfbaselines
Project-URL: Homepage, https://nerfbaselines.github.io/
Project-URL: Bug Tracker, https://github.com/nerfbaselines/nerfbaselines/issues
Classifier: Programming Language :: Python :: 3
Classifier: License :: OSI Approved :: MIT License
Classifier: Operating System :: OS Independent
Requires-Python: >=3.7
License-File: LICENSE
Requires-Dist: opencv-python>=4.6.0
Requires-Dist: typing-extensions>=4.4.0
Requires-Dist: click>=8.0.0
Requires-Dist: tqdm>=4.61.1
Requires-Dist: Pillow>=8.2.0
Requires-Dist: matplotlib>=3.4.2
Requires-Dist: plyfile>=0.7.3
Requires-Dist: numpy<2.0.0,>=1.19.5
Requires-Dist: tensorboard>=2.5.0
Requires-Dist: scipy
Requires-Dist: importlib-metadata>=6.0.0; python_version < "3.10"
Requires-Dist: importlib-resources; python_version < "3.9"
Provides-Extra: web
Requires-Dist: jinja2>=3.1.4; extra == "web"
Requires-Dist: livereload>=2.7.0; extra == "web"
Requires-Dist: sphinx-click>=6.0.0; extra == "web"
Requires-Dist: sphinx<8.0.0,>=4.2.0; extra == "web"
Requires-Dist: sphinx-rtd-theme>=2.0.0; extra == "web"
Requires-Dist: sphinxcontrib-apidoc>=0.5.0; extra == "web"
Requires-Dist: sphinxext-opengraph>=0.9.1; extra == "web"
Requires-Dist: sphinx-copybutton>=0.5.2; extra == "web"
Requires-Dist: furo>=2022.1.0; extra == "web"
Requires-Dist: myst_parser>=4.0.0; extra == "web"
Requires-Dist: myst_nb>=1.1.1; extra == "web"
Requires-Dist: sphinx-design>=0.6.1; extra == "web"
Provides-Extra: dev
Requires-Dist: pytest; extra == "dev"
Requires-Dist: typeguard<=4.2.1; extra == "dev"
Requires-Dist: pytest-benchmark; extra == "dev"
Requires-Dist: pyright<=1.1.377; extra == "dev"
Requires-Dist: jinja2==3.1.4; extra == "dev"
Requires-Dist: livereload==2.7.0; extra == "dev"
Requires-Dist: twine; extra == "dev"
Requires-Dist: build; extra == "dev"
Provides-Extra: extras
Requires-Dist: mediapy; extra == "extras"
Requires-Dist: wandb; extra == "extras"
Requires-Dist: gdown; extra == "extras"
Provides-Extra: extras-tests
Requires-Dist: addict; extra == "extras-tests"
Requires-Dist: hydra-core; extra == "extras-tests"
Requires-Dist: omegaconf; extra == "extras-tests"
Requires-Dist: einops; extra == "extras-tests"
Requires-Dist: dataclasses_json; extra == "extras-tests"
Requires-Dist: usd-core; extra == "extras-tests"
Requires-Dist: scikit-learn; extra == "extras-tests"
Requires-Dist: setuptools<70; extra == "extras-tests"
Requires-Dist: slangtorch; extra == "extras-tests"
Requires-Dist: imageio; extra == "extras-tests"
Requires-Dist: msgpack; extra == "extras-tests"
Requires-Dist: torch; extra == "extras-tests"
Requires-Dist: torchvision; extra == "extras-tests"
Requires-Dist: jax[cpu]; extra == "extras-tests"
Requires-Dist: torchmetrics==1.4.1; extra == "extras-tests"
Requires-Dist: dm_pix; extra == "extras-tests"
Requires-Dist: gin; extra == "extras-tests"
Dynamic: license-file
